asqav/__init__.py
asqav/client.py
asqav-0.2.5.dist-info/METADATA
asqav-0.2.5.dist-info/WHEEL
asqav-0.2.5.dist-info/RECORD
