Metadata-Version: 2.4
Name: asqav
Version: 0.2.5
Summary: Quantum-safe control for AI agents
Project-URL: Homepage, https://asqav.com
Project-URL: Documentation, https://asqav.com/docs
Project-URL: Repository, https://github.com/jagmarques/asqav-sdk
Author-email: Asqav <hello@asqav.com>
License-Expression: MIT
Keywords: agents,ai,audit,control,cryptography,identity,ml-dsa,post-quantum
Classifier: Development Status :: 4 - Beta
Classifier: Intended Audience :: Developers
Classifier: License :: OSI Approved :: MIT License
Classifier: Operating System :: OS Independent
Classifier: Programming Language :: Python :: 3
Classifier: Programming Language :: Python :: 3.10
Classifier: Programming Language :: Python :: 3.11
Classifier: Programming Language :: Python :: 3.12
Classifier: Topic :: Security :: Cryptography
Classifier: Topic :: Software Development :: Libraries :: Python Modules
Requires-Python: >=3.10
Provides-Extra: httpx
Requires-Dist: httpx>=0.24.0; extra == 'httpx'
